rifcomp/__init__ — копия.py
rifcomp/__init__.py
rifcomp/utils — копия.py
rifcomp/utils.py
rifcomp-0.1.0.dist-info/licenses/LICENSE.txt
rifcomp-0.1.0.dist-info/METADATA
rifcomp-0.1.0.dist-info/WHEEL
rifcomp-0.1.0.dist-info/top_level.txt
rifcomp-0.1.0.dist-info/RECORD
