Metadata-Version: 2.4
Name: rifcomp
Version: 0.1.0
Summary: Конвертер валют, единиц и файлов
Home-page: https://github.com/Rifleks/rifcomp
Author: Rifleks
Author-email: r.burdakov2022@yandex.ru
Classifier: Programming Language :: Python :: 3
Classifier: License :: OSI Approved :: MIT License
Classifier: Operating System :: OS Independent
Requires-Python: >=3.6
License-File: LICENSE.txt
Requires-Dist: requests
Requires-Dist: Pillow
Dynamic: author
Dynamic: author-email
Dynamic: classifier
Dynamic: description
Dynamic: description-content-type
Dynamic: home-page
Dynamic: license-file
Dynamic: requires-dist
Dynamic: requires-python
Dynamic: summary
